README.md
setup.cfg
setup.py
primalytics/__init__.py
primalytics/clustering.py
primalytics/dates.py
primalytics/emblem.py
primalytics/plots.py
primalytics/tools.py
primalytics.egg-info/PKG-INFO
primalytics.egg-info/SOURCES.txt
primalytics.egg-info/dependency_links.txt
primalytics.egg-info/requires.txt
primalytics.egg-info/top_level.txt
primalytics/preprocessing/__init__.py
primalytics/preprocessing/datareader.py
primalytics/preprocessing/encoders.py
primalytics/preprocessing/manipulations.py
primalytics/preprocessing/scalers.py