Metadata-Version: 1.1
Name: primalytics
Version: 1.0.16
Summary: Analytic library for Prima
Home-page: https://github.com/user/reponame
Author: Stefano Rossotti
Author-email: stefano.rossotti@hotmail.it
License: MIT
Download-URL: https://github.com/primait/prima-analytics/archive/1.0.12.tar.gz
Keywords: prima,analytics
Platform: UNKNOWN
Classifier: Development Status :: 3 - Alpha
Classifier: Intended Audience :: Developers
Classifier: Topic :: Software Development :: Build Tools
Classifier: License :: OSI Approved :: MIT License
Classifier: Programming Language :: Python :: 3
Classifier: Programming Language :: Python :: 3.4
Classifier: Programming Language :: Python :: 3.5
Classifier: Programming Language :: Python :: 3.6
Classifier: Programming Language :: Python :: 3.7
